[
  {
    "zipcode": "68183",
    "lat": 41.257093,
    "lon": -95.939786,
    "lat_p": 2027777.218551,
    "lon_p": 5005.095384,
    "gas_price": 3.19
  },
  {
    "zipcode": "68105",
    "lat": 41.240555,
    "lon": -95.964327,
    "lat_p": 2025871.939569,
    "lon_p": 2962.421142,
    "gas_price": 3.19
  },
  {
    "zipcode": "68528",
    "lat": 40.82245,
    "lon": -96.817683,
    "lat_p": 1979389.662489,
    "lon_p": -68348.006415,
    "gas_price": 3.19
  },
  {
    "zipcode": "68157",
    "lat": 41.179007,
    "lon": -95.995389,
    "lat_p": 2018759.013847,
    "lon_p": 730.695858,
    "gas_price": 3.19
  },
  {
    "zipcode": "68123",
    "lat": 41.101134,
    "lon": -95.94781,
    "lat_p": 2011462.987916,
    "lon_p": 4219.712596,
    "gas_price": 3.19
  },
  {
    "zipcode": "68059",
    "lat": 41.066718,
    "lon": -96.159525,
    "lat_p": 2005713.308993,
    "lon_p": -12567.945267,
    "gas_price": 3.19
  },
  {
    "zipcode": "68354",
    "lat": 40.639306,
    "lon": -97.580337,
    "lat_p": 1958644.747346,
    "lon_p": -134321.227998,
    "gas_price": 3.19
  },
  {
    "zipcode": "68343",
    "lat": 40.619856,
    "lon": -97.13195,
    "lat_p": 1957647.426533,
    "lon_p": -94143.757306,
    "gas_price": 3.19
  },
  {
    "zipcode": "68662",
    "lat": 41.206916,
    "lon": -97.415357,
    "lat_p": 2022194.701851,
    "lon_p": -118219.175887,
    "gas_price": 3.19
  },
  {
    "zipcode": "68122",
    "lat": 41.364505,
    "lon": -96.050359,
    "lat_p": 2040076.193059,
    "lon_p": -4329.352571,
    "gas_price": 3.19
  },
  {
    "zipcode": "68512",
    "lat": 40.737459,
    "lon": -96.705659,
    "lat_p": 1969931.555601,
    "lon_p": -59562.354466,
    "gas_price": 3.19
  },
  {
    "zipcode": "68664",
    "lat": 41.704573,
    "lon": -96.786835,
    "lat_p": 2078191.096625,
    "lon_p": -64961.041969,
    "gas_price": 3.19
  },
  {
    "zipcode": "68920",
    "lat": 40.154682,
    "lon": -99.335282,
    "lat_p": 1909240.122891,
    "lon_p": -283512.740941,
    "gas_price": 3.19
  },
  {
    "zipcode": "68643",
    "lat": 41.702216,
    "lon": -97.259155,
    "lat_p": 2077972.778132,
    "lon_p": -104290.962697,
    "gas_price": 3.19
  },
  {
    "zipcode": "68463",
    "lat": 40.875895,
    "lon": -96.135196,
    "lat_p": 1986191.90087,
    "lon_p": -10722.36779,
    "gas_price": 3.19
  },
  {
    "zipcode": "68448",
    "lat": 40.544298,
    "lon": -96.034991,
    "lat_p": 1948175.830538,
    "lon_p": -1680.026787,
    "gas_price": 3.19
  },
  {
    "zipcode": "68069",
    "lat": 41.241629,
    "lon": -96.315421,
    "lat_p": 2024769.519211,
    "lon_p": -26703.252931,
    "gas_price": 3.19
  },
  {
    "zipcode": "68381",
    "lat": 40.079787,
    "lon": -96.481727,
    "lat_p": 1896968.304356,
    "lon_p": -40797.881914,
    "gas_price": 3.19
  },
  {
    "zipcode": "68942",
    "lat": 40.095446,
    "lon": -98.311387,
    "lat_p": 1902088.332635,
    "lon_p": -193725.240973,
    "gas_price": 3.19
  },
  {
    "zipcode": "68934",
    "lat": 40.338298,
    "lon": -98.159636,
    "lat_p": 1926927.692994,
    "lon_p": -182045.194067,
    "gas_price": 3.19
  },
  {
    "zipcode": "68938",
    "lat": 40.420883,
    "lon": -98.12344,
    "lat_p": 1937183.744508,
    "lon_p": -177357.943091,
    "gas_price": 3.19
  },
  {
    "zipcode": "68779",
    "lat": 41.951536,
    "lon": -97.211753,
    "lat_p": 2106329.120596,
    "lon_p": -98550.124007,
    "gas_price": 3.19
  },
  {
    "zipcode": "68438",
    "lat": 40.626558,
    "lon": -96.744665,
    "lat_p": 1957384.939935,
    "lon_p": -62460.783606,
    "gas_price": 3.19
  },
  {
    "zipcode": "68066",
    "lat": 41.184506,
    "lon": -96.619973,
    "lat_p": 2018906.213041,
    "lon_p": -52454.737307,
    "gas_price": 3.19
  },
  {
    "zipcode": "68765",
    "lat": 42.33394,
    "lon": -97.623209,
    "lat_p": 2148874.999763,
    "lon_p": -130308.238835,
    "gas_price": 3.19
  },
  {
    "zipcode": "68769",
    "lat": 42.315743,
    "lon": -97.81638,
    "lat_p": 2146659.61834,
    "lon_p": -150520.849215,
    "gas_price": 3.19
  },
  {
    "zipcode": "68631",
    "lat": 41.687487,
    "lon": -97.35072,
    "lat_p": 2077609.704858,
    "lon_p": -111066.541075,
    "gas_price": 3.19
  },
  {
    "zipcode": "68946",
    "lat": 40.106759,
    "lon": -99.990443,
    "lat_p": 1906658.871984,
    "lon_p": -337420.249144,
    "gas_price": 3.19
  },
  {
    "zipcode": "68320",
    "lat": 40.481491,
    "lon": -95.953308,
    "lat_p": 1940685.992482,
    "lon_p": 3142.691729,
    "gas_price": 3.19
  },
  {
    "zipcode": "68854",
    "lat": 41.007972,
    "lon": -98.002409,
    "lat_p": 2002677.842572,
    "lon_p": -166312.38931,
    "gas_price": 3.19
  },
  {
    "zipcode": "68859",
    "lat": 41.460997,
    "lon": -98.819312,
    "lat_p": 2054909.784851,
    "lon_p": -232789.403826,
    "gas_price": 3.19
  },
  {
    "zipcode": "68716",
    "lat": 41.931375,
    "lon": -96.823459,
    "lat_p": 2103499.29667,
    "lon_p": -66025.237014,
    "gas_price": 3.19
  },
  {
    "zipcode": "68823",
    "lat": 41.936452,
    "lon": -99.13248,
    "lat_p": 2105973.929043,
    "lon_p": -253028.995017,
    "gas_price": 3.19
  },
  {
    "zipcode": "68822",
    "lat": 41.388787,
    "lon": -99.627665,
    "lat_p": 2046250.10073,
    "lon_p": -302376.979954,
    "gas_price": 3.19
  },
  {
    "zipcode": "68766",
    "lat": 42.423703,
    "lon": -98.403206,
    "lat_p": 2159815.444071,
    "lon_p": -195276.918248,
    "gas_price": 3.19
  },
  {
    "zipcode": "68835",
    "lat": 41.333241,
    "lon": -98.617687,
    "lat_p": 2041183.317179,
    "lon_p": -218438.783445,
    "gas_price": 3.19
  },
  {
    "zipcode": "68759",
    "lat": 42.750427,
    "lon": -99.337449,
    "lat_p": 2195946.626251,
    "lon_p": -270628.560563,
    "gas_price": 3.19
  },
  {
    "zipcode": "68636",
    "lat": 42.004928,
    "lon": -98.156723,
    "lat_p": 2115190.384964,
    "lon_p": -179361.257039,
    "gas_price": 3.19
  },
  {
    "zipcode": "68324",
    "lat": 40.554075,
    "lon": -96.290145,
    "lat_p": 1949641.55853,
    "lon_p": -24440.491171,
    "gas_price": 3.19
  },
  {
    "zipcode": "68720",
    "lat": 42.346562,
    "lon": -98.014183,
    "lat_p": 2150947.43582,
    "lon_p": -164494.319447,
    "gas_price": 3.19
  },
  {
    "zipcode": "68817",
    "lat": 41.261195,
    "lon": -98.793741,
    "lat_p": 2031960.897776,
    "lon_p": -231479.027909,
    "gas_price": 3.19
  },
  {
    "zipcode": "68771",
    "lat": 42.384132,
    "lon": -97.357053,
    "lat_p": 2154323.485842,
    "lon_p": -110400.233301,
    "gas_price": 3.19
  },
  {
    "zipcode": "68861",
    "lat": 40.698946,
    "lon": -99.263886,
    "lat_p": 1969787.595077,
    "lon_p": -273492.745775,
    "gas_price": 3.19
  },
  {
    "zipcode": "68787",
    "lat": 42.213659,
    "lon": -97.033483,
    "lat_p": 2136056.043451,
    "lon_p": -85871.795267,
    "gas_price": 3.19
  },
  {
    "zipcode": "68508",
    "lat": 40.818297,
    "lon": -96.706252,
    "lat_p": 1978994.357955,
    "lon_p": -59083.838428,
    "gas_price": 3.19
  },
  {
    "zipcode": "68876",
    "lat": 40.824816,
    "lon": -98.746657,
    "lat_p": 1980681.324597,
    "lon_p": -227701.674767,
    "gas_price": 3.19
  },
  {
    "zipcode": "68502",
    "lat": 40.783565,
    "lon": -96.70085,
    "lat_p": 1974618.508234,
    "lon_p": -58317.749731,
    "gas_price": 3.19
  },
  {
    "zipcode": "68506",
    "lat": 40.784202,
    "lon": -96.639619,
    "lat_p": 1974917.091265,
    "lon_p": -53518.273594,
    "gas_price": 3.19
  },
  {
    "zipcode": "68178",
    "lat": 41.265361,
    "lon": -95.945394,
    "lat_p": 2028692.997427,
    "lon_p": 4554.28231,
    "gas_price": 3.19
  },
  {
    "zipcode": "68980",
    "lat": 40.682123,
    "lon": -98.258139,
    "lat_p": 1965801.030795,
    "lon_p": -188585.353485,
    "gas_price": 3.19
  },
  {
    "zipcode": "68147",
    "lat": 41.17653,
    "lon": -95.956793,
    "lat_p": 2018769.905041,
    "lon_p": 3478.332685,
    "gas_price": 3.19
  },
  {
    "zipcode": "68743",
    "lat": 42.472687,
    "lon": -96.625813,
    "lat_p": 2163257.992983,
    "lon_p": -51486.437573,
    "gas_price": 3.19
  },
  {
    "zipcode": "68731",
    "lat": 42.409924,
    "lon": -96.483477,
    "lat_p": 2157702.760273,
    "lon_p": -39840.831606,
    "gas_price": 3.19
  },
  {
    "zipcode": "68005",
    "lat": 41.141644,
    "lon": -95.893886,
    "lat_p": 2012728.870587,
    "lon_p": 9359.965473,
    "gas_price": 3.19
  },
  {
    "zipcode": "68361",
    "lat": 40.507567,
    "lon": -97.601465,
    "lat_p": 1944518.219784,
    "lon_p": -136111.68628,
    "gas_price": 3.19
  },
  {
    "zipcode": "68439",
    "lat": 40.99937,
    "lon": -97.211363,
    "lat_p": 1999849.003632,
    "lon_p": -100631.639401,
    "gas_price": 3.19
  },
  {
    "zipcode": "68715",
    "lat": 41.97002,
    "lon": -97.608777,
    "lat_p": 2107298.071118,
    "lon_p": -132550.837485,
    "gas_price": 3.19
  },
  {
    "zipcode": "68132",
    "lat": 41.265038,
    "lon": -96.001532,
    "lat_p": 2028499.150892,
    "lon_p": -189.65457,
    "gas_price": 3.19
  },
  {
    "zipcode": "68310",
    "lat": 40.249564,
    "lon": -96.74944,
    "lat_p": 1915819.684377,
    "lon_p": -61377.886976,
    "gas_price": 3.19
  },
  {
    "zipcode": "68661",
    "lat": 41.495539,
    "lon": -97.083487,
    "lat_p": 2056041.147503,
    "lon_p": -88618.004854,
    "gas_price": 3.19
  },
  {
    "zipcode": "68922",
    "lat": 40.336429,
    "lon": -99.899778,
    "lat_p": 1929665.113811,
    "lon_p": -327149.338627,
    "gas_price": 3.19
  },
  {
    "zipcode": "68520",
    "lat": 40.798265,
    "lon": -96.55313,
    "lat_p": 1975792.883689,
    "lon_p": -49112.652986,
    "gas_price": 3.19
  },
  {
    "zipcode": "68307",
    "lat": 40.787727,
    "lon": -96.140495,
    "lat_p": 1974825.140253,
    "lon_p": -12960.83119,
    "gas_price": 3.19
  },
  {
    "zipcode": "68455",
    "lat": 40.822869,
    "lon": -95.901263,
    "lat_p": 1978833.117031,
    "lon_p": 8283.461312,
    "gas_price": 3.19
  },
  {
    "zipcode": "68864",
    "lat": 41.260727,
    "lon": -98.240489,
    "lat_p": 2032314.377862,
    "lon_p": -183796.903044,
    "gas_price": 3.19
  },
  {
    "zipcode": "68928",
    "lat": 40.28737,
    "lon": -98.607299,
    "lat_p": 1921952.194349,
    "lon_p": -218317.342755,
    "gas_price": 3.19
  },
  {
    "zipcode": "68628",
    "lat": 41.216909,
    "lon": -97.843546,
    "lat_p": 2022994.166212,
    "lon_p": -152163.571665,
    "gas_price": 3.19
  },
  {
    "zipcode": "68341",
    "lat": 40.38551,
    "lon": -96.913771,
    "lat_p": 1930196.373779,
    "lon_p": -78483.417801,
    "gas_price": 3.19
  },
  {
    "zipcode": "68130",
    "lat": 41.233943,
    "lon": -96.196185,
    "lat_p": 2025153.014258,
    "lon_p": -16347.715251,
    "gas_price": 3.19
  },
  {
    "zipcode": "68135",
    "lat": 41.205213,
    "lon": -96.195741,
    "lat_p": 2022116.802139,
    "lon_p": -16326.971005,
    "gas_price": 3.19
  },
  {
    "zipcode": "68057",
    "lat": 41.658843,
    "lon": -96.718982,
    "lat_p": 2073465.62704,
    "lon_p": -59760.320945,
    "gas_price": 3.19
  },
  {
    "zipcode": "68358",
    "lat": 40.533208,
    "lon": -96.609733,
    "lat_p": 1945793.753396,
    "lon_p": -49092.648829,
    "gas_price": 3.19
  },
  {
    "zipcode": "68970",
    "lat": 40.101562,
    "lon": -98.522893,
    "lat_p": 1902180.60907,
    "lon_p": -212810.986666,
    "gas_price": 3.19
  },
  {
    "zipcode": "68733",
    "lat": 42.282775,
    "lon": -96.722434,
    "lat_p": 2143050.335522,
    "lon_p": -56276.012617,
    "gas_price": 3.19
  },
  {
    "zipcode": "68338",
    "lat": 40.318658,
    "lon": -97.248659,
    "lat_p": 1922109.657999,
    "lon_p": -109764.267565,
    "gas_price": 3.19
  },
  {
    "zipcode": "68061",
    "lat": 41.800749,
    "lon": -96.211663,
    "lat_p": 2088535.109122,
    "lon_p": -16283.019194,
    "gas_price": 3.19
  },
  {
    "zipcode": "68034",
    "lat": 41.455562,
    "lon": -96.220293,
    "lat_p": 2049982.326773,
    "lon_p": -18502.524818,
    "gas_price": 3.19
  },
  {
    "zipcode": "68055",
    "lat": 42.057463,
    "lon": -96.471997,
    "lat_p": 2117762.841075,
    "lon_p": -38671.957166,
    "gas_price": 3.19
  },
  {
    "zipcode": "68375",
    "lat": 40.039391,
    "lon": -97.488258,
    "lat_p": 1893036.410694,
    "lon_p": -125138.77802,
    "gas_price": 3.19
  },
  {
    "zipcode": "68039",
    "lat": 42.11198,
    "lon": -96.344064,
    "lat_p": 2124295.154585,
    "lon_p": -27057.477204,
    "gas_price": 3.19
  },
  {
    "zipcode": "68975",
    "lat": 40.61704,
    "lon": -97.954834,
    "lat_p": 1958474.294698,
    "lon_p": -163780.629427,
    "gas_price": 3.19
  },
  {
    "zipcode": "68362",
    "lat": 40.153221,
    "lon": -97.425504,
    "lat_p": 1904941.820658,
    "lon_p": -120412.15119,
    "gas_price": 3.19
  },
  {
    "zipcode": "68445",
    "lat": 40.401473,
    "lon": -97.086612,
    "lat_p": 1932422.551425,
    "lon_p": -92039.15201,
    "gas_price": 3.19
  },
  {
    "zipcode": "68303",
    "lat": 40.257491,
    "lon": -97.410333,
    "lat_p": 1916550.326686,
    "lon_p": -118606.19655,
    "gas_price": 3.19
  },
  {
    "zipcode": "68954",
    "lat": 40.612189,
    "lon": -98.235166,
    "lat_p": 1958459.176768,
    "lon_p": -188013.198238,
    "gas_price": 3.19
  },
  {
    "zipcode": "68377",
    "lat": 40.217001,
    "lon": -97.022971,
    "lat_p": 1912006.495697,
    "lon_p": -87664.03778,
    "gas_price": 3.19
  },
  {
    "zipcode": "68431",
    "lat": 40.067761,
    "lon": -95.433999,
    "lat_p": 1896916.035187,
    "lon_p": 46783.600657,
    "gas_price": 3.19
  },
  {
    "zipcode": "68364",
    "lat": 40.836552,
    "lon": -97.225631,
    "lat_p": 1981352.274734,
    "lon_p": -102505.564661,
    "gas_price": 3.19
  },
  {
    "zipcode": "68658",
    "lat": 41.199675,
    "lon": -97.293671,
    "lat_p": 2023486.024764,
    "lon_p": -107424.075303,
    "gas_price": 3.19
  },
  {
    "zipcode": "68788",
    "lat": 41.838662,
    "lon": -96.725746,
    "lat_p": 2095767.123692,
    "lon_p": -58529.030321,
    "gas_price": 3.19
  },
  {
    "zipcode": "68018",
    "lat": 41.3021,
    "lon": -96.615755,
    "lat_p": 2033569.627068,
    "lon_p": -50683.869251,
    "gas_price": 3.19
  },
  {
    "zipcode": "68050",
    "lat": 41.305903,
    "lon": -96.843021,
    "lat_p": 2032942.671209,
    "lon_p": -69172.491991,
    "gas_price": 3.19
  },
  {
    "zipcode": "68855",
    "lat": 41.162422,
    "lon": -99.326419,
    "lat_p": 2023496.652723,
    "lon_p": -278662.619471,
    "gas_price": 3.19
  },
  {
    "zipcode": "68834",
    "lat": 41.018205,
    "lon": -99.650523,
    "lat_p": 2010693.664362,
    "lon_p": -303989.79853,
    "gas_price": 3.19
  },
  {
    "zipcode": "68874",
    "lat": 41.633642,
    "lon": -99.426324,
    "lat_p": 2072717.603007,
    "lon_p": -285550.552677,
    "gas_price": 3.19
  },
  {
    "zipcode": "68015",
    "lat": 41.383508,
    "lon": -96.647382,
    "lat_p": 2041590.169869,
    "lon_p": -54718.764268,
    "gas_price": 3.19
  },
  {
    "zipcode": "68414",
    "lat": 40.319654,
    "lon": -95.699111,
    "lat_p": 1922924.290884,
    "lon_p": 24736.663489,
    "gas_price": 3.19
  },
  {
    "zipcode": "68812",
    "lat": 40.905016,
    "lon": -99.278997,
    "lat_p": 1993542.63628,
    "lon_p": -273080.633214,
    "gas_price": 3.19
  },
  {
    "zipcode": "68632",
    "lat": 41.242639,
    "lon": -97.132871,
    "lat_p": 2025850.381592,
    "lon_p": -93480.237165,
    "gas_price": 3.19
  },
  {
    "zipcode": "68421",
    "lat": 40.491956,
    "lon": -95.744195,
    "lat_p": 1942956.677059,
    "lon_p": 19493.044949,
    "gas_price": 3.19
  },
  {
    "zipcode": "68417",
    "lat": 40.735905,
    "lon": -96.091988,
    "lat_p": 1969097.534525,
    "lon_p": -7766.669397,
    "gas_price": 3.19
  },
  {
    "zipcode": "68878",
    "lat": 40.986182,
    "lon": -99.505627,
    "lat_p": 2004378.177023,
    "lon_p": -292109.137294,
    "gas_price": 3.19
  },
  {
    "zipcode": "68734",
    "lat": 42.425227,
    "lon": -98.804458,
    "lat_p": 2163744.988813,
    "lon_p": -227219.77218,
    "gas_price": 3.19
  },
  {
    "zipcode": "68820",
    "lat": 41.106591,
    "lon": -98.700577,
    "lat_p": 2015960.386375,
    "lon_p": -225668.8579,
    "gas_price": 3.19
  },
  {
    "zipcode": "68719",
    "lat": 42.964383,
    "lon": -98.57425,
    "lat_p": 2219389.396625,
    "lon_p": -209301.614957,
    "gas_price": 3.19
  },
  {
    "zipcode": "68778",
    "lat": 42.869579,
    "lon": -99.794716,
    "lat_p": 2213083.447402,
    "lon_p": -310006.78978,
    "gas_price": 3.19
  },
  {
    "zipcode": "68637",
    "lat": 41.787693,
    "lon": -98.689801,
    "lat_p": 2090935.204585,
    "lon_p": -219309.942181,
    "gas_price": 3.19
  },
  {
    "zipcode": "68332",
    "lat": 40.328266,
    "lon": -96.411218,
    "lat_p": 1923745.180445,
    "lon_p": -34312.844056,
    "gas_price": 3.19
  },
  {
    "zipcode": "68773",
    "lat": 42.362371,
    "lon": -98.119912,
    "lat_p": 2151957.735235,
    "lon_p": -174035.283822,
    "gas_price": 3.19
  },
  {
    "zipcode": "68635",
    "lat": 41.085437,
    "lon": -97.022979,
    "lat_p": 2009423.963689,
    "lon_p": -85290.548188,
    "gas_price": 3.19
  },
  {
    "zipcode": "68667",
    "lat": 41.112309,
    "lon": -97.302779,
    "lat_p": 2011060.886165,
    "lon_p": -110016.992217,
    "gas_price": 3.19
  },
  {
    "zipcode": "68379",
    "lat": 40.529115,
    "lon": -95.869802,
    "lat_p": 1946041.356066,
    "lon_p": 10827.047254,
    "gas_price": 3.19
  },
  {
    "zipcode": "68380",
    "lat": 40.242818,
    "lon": -96.405933,
    "lat_p": 1913989.178292,
    "lon_p": -34354.93235,
    "gas_price": 3.19
  },
  {
    "zipcode": "68382",
    "lat": 40.59722,
    "lon": -96.024177,
    "lat_p": 1953883.754249,
    "lon_p": -2011.532238,
    "gas_price": 3.19
  },
  {
    "zipcode": "68745",
    "lat": 42.446549,
    "lon": -97.087844,
    "lat_p": 2162420.201792,
    "lon_p": -88579.149623,
    "gas_price": 3.19
  },
  {
    "zipcode": "68722",
    "lat": 42.920711,
    "lon": -98.871181,
    "lat_p": 2216393.615494,
    "lon_p": -233825.786428,
    "gas_price": 3.19
  },
  {
    "zipcode": "68790",
    "lat": 42.173824,
    "lon": -97.186152,
    "lat_p": 2130549.972651,
    "lon_p": -97923.845244,
    "gas_price": 3.19
  },
  {
    "zipcode": "68783",
    "lat": 42.625192,
    "lon": -98.146099,
    "lat_p": 2183821.223828,
    "lon_p": -173607.890735,
    "gas_price": 3.19
  },
  {
    "zipcode": "68111",
    "lat": 41.295653,
    "lon": -95.964004,
    "lat_p": 2031976.652166,
    "lon_p": 2966.229548,
    "gas_price": 3.19
  },
  {
    "zipcode": "68131",
    "lat": 41.26432,
    "lon": -95.964744,
    "lat_p": 2028595.60621,
    "lon_p": 2791.572698,
    "gas_price": 3.19
  },
  {
    "zipcode": "68510",
    "lat": 40.806533,
    "lon": -96.648479,
    "lat_p": 1977451.249115,
    "lon_p": -54369.771953,
    "gas_price": 3.19
  },
  {
    "zipcode": "68025",
    "lat": 41.437432,
    "lon": -96.491496,
    "lat_p": 2048488.467451,
    "lon_p": -40264.831372,
    "gas_price": 3.19
  },
  {
    "zipcode": "68108",
    "lat": 41.237497,
    "lon": -95.931022,
    "lat_p": 2025016.539445,
    "lon_p": 5916.242895,
    "gas_price": 3.19
  },
  {
    "zipcode": "68524",
    "lat": 40.871509,
    "lon": -96.802589,
    "lat_p": 1985358.387465,
    "lon_p": -66036.594934,
    "gas_price": 3.19
  },
  {
    "zipcode": "68028",
    "lat": 41.105114,
    "lon": -96.261008,
    "lat_p": 2009899.219651,
    "lon_p": -22939.728963,
    "gas_price": 3.19
  },
  {
    "zipcode": "68406",
    "lat": 40.505675,
    "lon": -97.378774,
    "lat_p": 1942533.204181,
    "lon_p": -109442.520999,
    "gas_price": 3.19
  },
  {
    "zipcode": "68046",
    "lat": 41.122044,
    "lon": -96.06138,
    "lat_p": 2011844.259692,
    "lon_p": -3965.615636,
    "gas_price": 3.19
  },
  {
    "zipcode": "68416",
    "lat": 40.410896,
    "lon": -97.461862,
    "lat_p": 1935317.937722,
    "lon_p": -122922.510691,
    "gas_price": 3.19
  },
  {
    "zipcode": "68365",
    "lat": 40.615608,
    "lon": -97.730648,
    "lat_p": 1956821.258645,
    "lon_p": -145061.237788,
    "gas_price": 3.19
  },
  {
    "zipcode": "68142",
    "lat": 41.370126,
    "lon": -96.102744,
    "lat_p": 2040404.942269,
    "lon_p": -8898.35942,
    "gas_price": 3.19
  },
  {
    "zipcode": "68164",
    "lat": 41.298855,
    "lon": -96.109491,
    "lat_p": 2032486.546566,
    "lon_p": -9152.154767,
    "gas_price": 3.19
  },
  {
    "zipcode": "68116",
    "lat": 41.298425,
    "lon": -96.166284,
    "lat_p": 2032433.951491,
    "lon_p": -13934.128838,
    "gas_price": 3.19
  },
  {
    "zipcode": "68357",
    "lat": 40.31539,
    "lon": -96.546578,
    "lat_p": 1922228.606707,
    "lon_p": -46786.29334,
    "gas_price": 3.19
  },
  {
    "zipcode": "68649",
    "lat": 41.507832,
    "lon": -96.788961,
    "lat_p": 2056799.969165,
    "lon_p": -65451.185811,
    "gas_price": 3.19
  },
  {
    "zipcode": "68947",
    "lat": 40.301381,
    "lon": -99.051893,
    "lat_p": 1924376.672358,
    "lon_p": -255978.725109,
    "gas_price": 3.19
  },
  {
    "zipcode": "68633",
    "lat": 41.705808,
    "lon": -96.896661,
    "lat_p": 2076794.810185,
    "lon_p": -72300.274015,
    "gas_price": 3.19
  },
  {
    "zipcode": "68127",
    "lat": 41.206102,
    "lon": -96.05246,
    "lat_p": 2022062.709009,
    "lon_p": -4376.811931,
    "gas_price": 3.19
  },
  {
    "zipcode": "68640",
    "lat": 41.461048,
    "lon": -97.772388,
    "lat_p": 2053477.769387,
    "lon_p": -148512.995252,
    "gas_price": 3.19
  },
  {
    "zipcode": "68419",
    "lat": 40.602959,
    "lon": -96.511279,
    "lat_p": 1954767.280678,
    "lon_p": -42900.169303,
    "gas_price": 3.19
  },
  {
    "zipcode": "68008",
    "lat": 41.545658,
    "lon": -96.174221,
    "lat_p": 2059236.782908,
    "lon_p": -16705.361521,
    "gas_price": 3.19
  },
  {
    "zipcode": "68002",
    "lat": 41.501632,
    "lon": -96.339715,
    "lat_p": 2056141.197262,
    "lon_p": -28716.915681,
    "gas_price": 3.19
  },
  {
    "zipcode": "68818",
    "lat": 40.822036,
    "lon": -98.010302,
    "lat_p": 1979222.117344,
    "lon_p": -168676.688625,
    "gas_price": 3.19
  },
  {
    "zipcode": "68816",
    "lat": 41.174852,
    "lon": -98.133715,
    "lat_p": 2020801.776484,
    "lon_p": -177754.165765,
    "gas_price": 3.19
  },
  {
    "zipcode": "68350",
    "lat": 40.039623,
    "lon": -97.091719,
    "lat_p": 1892533.100329,
    "lon_p": -93056.075857,
    "gas_price": 3.19
  },
  {
    "zipcode": "68741",
    "lat": 42.357112,
    "lon": -96.593769,
    "lat_p": 2151513.843535,
    "lon_p": -50240.360141,
    "gas_price": 3.19
  },
  {
    "zipcode": "68413",
    "lat": 40.837719,
    "lon": -96.010538,
    "lat_p": 1981737.278718,
    "lon_p": -590.772639,
    "gas_price": 3.19
  },
  {
    "zipcode": "68647",
    "lat": 41.519678,
    "lon": -97.620191,
    "lat_p": 2058991.79799,
    "lon_p": -134084.664261,
    "gas_price": 3.19
  },
  {
    "zipcode": "68318",
    "lat": 40.15602,
    "lon": -96.64445,
    "lat_p": 1904446.834484,
    "lon_p": -55489.316497,
    "gas_price": 3.19
  },
  {
    "zipcode": "68313",
    "lat": 40.781397,
    "lon": -97.271912,
    "lat_p": 1974794.580818,
    "lon_p": -106563.532176,
    "gas_price": 3.19
  },
  {
    "zipcode": "68405",
    "lat": 40.765214,
    "lon": -97.073175,
    "lat_p": 1974189.338213,
    "lon_p": -90218.929998,
    "gas_price": 3.19
  },
  {
    "zipcode": "68044",
    "lat": 41.54796,
    "lon": -96.448692,
    "lat_p": 2059368.176986,
    "lon_p": -36669.189492,
    "gas_price": 3.19
  },
  {
    "zipcode": "68020",
    "lat": 41.976183,
    "lon": -96.256163,
    "lat_p": 2109145.21947,
    "lon_p": -21423.790504,
    "gas_price": 3.19
  },
  {
    "zipcode": "68370",
    "lat": 40.141488,
    "lon": -97.555637,
    "lat_p": 1904620.359389,
    "lon_p": -131136.669894,
    "gas_price": 3.19
  },
  {
    "zipcode": "68784",
    "lat": 42.257569,
    "lon": -96.886545,
    "lat_p": 2138831.236833,
    "lon_p": -73034.59844,
    "gas_price": 3.19
  },
  {
    "zipcode": "68452",
    "lat": 40.397534,
    "lon": -97.85035,
    "lat_p": 1932632.705905,
    "lon_p": -155114.734984,
    "gas_price": 3.19
  },
  {
    "zipcode": "68422",
    "lat": 40.388623,
    "lon": -96.697535,
    "lat_p": 1930403.444954,
    "lon_p": -58507.622805,
    "gas_price": 3.19
  },
  {
    "zipcode": "68833",
    "lat": 41.802692,
    "lon": -100.094513,
    "lat_p": 2098729.177524,
    "lon_p": -337392.275035,
    "gas_price": 3.19
  },
  {
    "zipcode": "68623",
    "lat": 41.443269,
    "lon": -98.11606,
    "lat_p": 2051070.840359,
    "lon_p": -171294.364043,
    "gas_price": 3.19
  },
  {
    "zipcode": "68460",
    "lat": 40.895893,
    "lon": -97.431661,
    "lat_p": 1987223.581971,
    "lon_p": -119126.235397,
    "gas_price": 3.19
  },
  {
    "zipcode": "68791",
    "lat": 41.990989,
    "lon": -96.93247,
    "lat_p": 2109290.317885,
    "lon_p": -76735.636224,
    "gas_price": 3.19
  },
  {
    "zipcode": "68433",
    "lat": 40.052506,
    "lon": -95.739693,
    "lat_p": 1893587.942567,
    "lon_p": 22181.809541,
    "gas_price": 3.19
  },
  {
    "zipcode": "68003",
    "lat": 41.071538,
    "lon": -96.380088,
    "lat_p": 2006495.361961,
    "lon_p": -35466.041709,
    "gas_price": 3.19
  },
  {
    "zipcode": "68033",
    "lat": 41.129319,
    "lon": -96.524248,
    "lat_p": 2014095.86234,
    "lon_p": -43570.399688,
    "gas_price": 3.19
  },
  {
    "zipcode": "68305",
    "lat": 40.363912,
    "lon": -95.857897,
    "lat_p": 1929306.574007,
    "lon_p": 12387.357018,
    "gas_price": 3.19
  },
  {
    "zipcode": "68860",
    "lat": 41.133768,
    "lon": -99.791662,
    "lat_p": 2019646.115773,
    "lon_p": -314854.972734,
    "gas_price": 3.19
  },
  {
    "zipcode": "68815",
    "lat": 41.429406,
    "lon": -99.160459,
    "lat_p": 2052371.299941,
    "lon_p": -262422.59147,
    "gas_price": 3.19
  },
  {
    "zipcode": "68813",
    "lat": 41.704673,
    "lon": -99.835716,
    "lat_p": 2083191.93665,
    "lon_p": -317982.09536,
    "gas_price": 3.19
  },
  {
    "zipcode": "68827",
    "lat": 41.042474,
    "lon": -98.181104,
    "lat_p": 2006157.154549,
    "lon_p": -181768.922232,
    "gas_price": 3.19
  },
  {
    "zipcode": "68726",
    "lat": 42.178734,
    "lon": -98.19956,
    "lat_p": 2132716.678592,
    "lon_p": -180798.925807,
    "gas_price": 3.19
  },
  {
    "zipcode": "68665",
    "lat": 41.705353,
    "lon": -98.414307,
    "lat_p": 2082006.193349,
    "lon_p": -199636.019138,
    "gas_price": 3.19
  },
  {
    "zipcode": "68767",
    "lat": 42.196885,
    "lon": -97.536271,
    "lat_p": 2135109.790639,
    "lon_p": -127389.771358,
    "gas_price": 3.19
  },
  {
    "zipcode": "68346",
    "lat": 40.661928,
    "lon": -96.030668,
    "lat_p": 1961043.880293,
    "lon_p": -1727.75569,
    "gas_price": 3.19
  },
  {
    "zipcode": "68454",
    "lat": 40.692715,
    "lon": -96.286866,
    "lat_p": 1965055.923933,
    "lon_p": -23763.228744,
    "gas_price": 3.19
  },
  {
    "zipcode": "68407",
    "lat": 40.920983,
    "lon": -96.262625,
    "lat_p": 1990178.13873,
    "lon_p": -22101.334198,
    "gas_price": 3.19
  },
  {
    "zipcode": "68774",
    "lat": 42.814011,
    "lon": -97.277437,
    "lat_p": 2202470.516058,
    "lon_p": -102889.85278,
    "gas_price": 3.19
  },
  {
    "zipcode": "68724",
    "lat": 42.627618,
    "lon": -97.884932,
    "lat_p": 2182383.025698,
    "lon_p": -154188.096008,
    "gas_price": 3.19
  },
  {
    "zipcode": "68789",
    "lat": 42.536428,
    "lon": -97.991866,
    "lat_p": 2172935.134475,
    "lon_p": -167674.728527,
    "gas_price": 3.19
  },
  {
    "zipcode": "68112",
    "lat": 41.382067,
    "lon": -95.958153,
    "lat_p": 2041972.588184,
    "lon_p": 3385.300462,
    "gas_price": 3.19
  },
  {
    "zipcode": "68117",
    "lat": 41.206192,
    "lon": -96.001395,
    "lat_p": 2022088.280404,
    "lon_p": -53.88232,
    "gas_price": 3.19
  },
  {
    "zipcode": "68517",
    "lat": 40.93339,
    "lon": -96.60485,
    "lat_p": 1991672.292715,
    "lon_p": -50169.416964,
    "gas_price": 3.19
  },
  {
    "zipcode": "68336",
    "lat": 40.961507,
    "lon": -96.684059,
    "lat_p": 1993213.825099,
    "lon_p": -56118.453216,
    "gas_price": 3.19
  },
  {
    "zipcode": "68785",
    "lat": 42.427964,
    "lon": -96.722394,
    "lat_p": 2160085.0604,
    "lon_p": -59191.832301,
    "gas_price": 3.19
  },
  {
    "zipcode": "68666",
    "lat": 41.107746,
    "lon": -97.613645,
    "lat_p": 2011837.29225,
    "lon_p": -133182.45909,
    "gas_price": 3.19
  },
  {
    "zipcode": "68359",
    "lat": 40.630545,
    "lon": -97.283328,
    "lat_p": 1957857.774722,
    "lon_p": -107642.93898,
    "gas_price": 3.19
  },
  {
    "zipcode": "68652",
    "lat": 41.861747,
    "lon": -98.089102,
    "lat_p": 2094794.519978,
    "lon_p": -178203.341355,
    "gas_price": 3.19
  },
  {
    "zipcode": "68335",
    "lat": 40.282374,
    "lon": -97.803,
    "lat_p": 1920713.096005,
    "lon_p": -154295.056682,
    "gas_price": 3.19
  },
  {
    "zipcode": "68367",
    "lat": 41.038055,
    "lon": -97.4012,
    "lat_p": 2005834.661596,
    "lon_p": -119665.77595,
    "gas_price": 3.19
  },
  {
    "zipcode": "68948",
    "lat": 40.341392,
    "lon": -100.026354,
    "lat_p": 1929458.733896,
    "lon_p": -338973.862465,
    "gas_price": 3.19
  },
  {
    "zipcode": "68982",
    "lat": 40.330762,
    "lon": -99.19517,
    "lat_p": 1927516.896046,
    "lon_p": -270198.893456,
    "gas_price": 3.19
  },
  {
    "zipcode": "68415",
    "lat": 40.062509,
    "lon": -96.821614,
    "lat_p": 1896373.467811,
    "lon_p": -67863.201195,
    "gas_price": 3.19
  },
  {
    "zipcode": "68949",
    "lat": 40.431854,
    "lon": -99.394834,
    "lat_p": 1943549.029255,
    "lon_p": -282863.976552,
    "gas_price": 3.19
  },
  {
    "zipcode": "68062",
    "lat": 42.195397,
    "lon": -96.674305,
    "lat_p": 2133410.48512,
    "lon_p": -54367.179055,
    "gas_price": 3.19
  },
  {
    "zipcode": "68047",
    "lat": 42.105921,
    "lon": -96.732519,
    "lat_p": 2122339.587749,
    "lon_p": -59187.896193,
    "gas_price": 3.19
  },
  {
    "zipcode": "68458",
    "lat": 40.231054,
    "lon": -96.487412,
    "lat_p": 1913158.897005,
    "lon_p": -41529.21111,
    "gas_price": 3.19
  },
  {
    "zipcode": "68410",
    "lat": 40.637222,
    "lon": -95.88578,
    "lat_p": 1960281.441099,
    "lon_p": 10235.520388,
    "gas_price": 3.19
  },
  {
    "zipcode": "68523",
    "lat": 40.735531,
    "lon": -96.757074,
    "lat_p": 1969948.248118,
    "lon_p": -63561.239349,
    "gas_price": 3.19
  },
  {
    "zipcode": "68955",
    "lat": 40.592863,
    "lon": -98.539676,
    "lat_p": 1956656.169203,
    "lon_p": -212664.585392,
    "gas_price": 3.19
  },
  {
    "zipcode": "68457",
    "lat": 40.156184,
    "lon": -95.710938,
    "lat_p": 1904972.863218,
    "lon_p": 24515.290556,
    "gas_price": 3.19
  },
  {
    "zipcode": "68355",
    "lat": 40.116707,
    "lon": -95.567054,
    "lat_p": 1902075.507049,
    "lon_p": 35714.457498,
    "gas_price": 3.19
  },
  {
    "zipcode": "68428",
    "lat": 40.972472,
    "lon": -96.796256,
    "lat_p": 1996204.130431,
    "lon_p": -67428.161886,
    "gas_price": 3.19
  },
  {
    "zipcode": "68065",
    "lat": 41.076623,
    "lon": -96.848525,
    "lat_p": 2009022.341589,
    "lon_p": -70139.772433,
    "gas_price": 3.19
  },
  {
    "zipcode": "68017",
    "lat": 41.059377,
    "lon": -96.661765,
    "lat_p": 2005106.5038,
    "lon_p": -54026.741566,
    "gas_price": 3.19
  },
  {
    "zipcode": "68929",
    "lat": 40.152441,
    "lon": -99.071211,
    "lat_p": 1907004.793395,
    "lon_p": -256517.708559,
    "gas_price": 3.19
  },
  {
    "zipcode": "68309",
    "lat": 40.049051,
    "lon": -96.572866,
    "lat_p": 1892603.567624,
    "lon_p": -48463.833028,
    "gas_price": 3.19
  },
  {
    "zipcode": "68748",
    "lat": 41.838832,
    "lon": -97.476377,
    "lat_p": 2094090.134814,
    "lon_p": -122399.723512,
    "gas_price": 3.19
  },
  {
    "zipcode": "68360",
    "lat": 40.946123,
    "lon": -96.956623,
    "lat_p": 1993599.90971,
    "lon_p": -80028.483224,
    "gas_price": 3.19
  },
  {
    "zipcode": "68378",
    "lat": 40.393529,
    "lon": -96.026157,
    "lat_p": 1930600.218898,
    "lon_p": -787.143965,
    "gas_price": 3.19
  },
  {
    "zipcode": "68866",
    "lat": 40.968704,
    "lon": -99.122894,
    "lat_p": 2001543.000055,
    "lon_p": -259726.760956,
    "gas_price": 3.19
  },
  {
    "zipcode": "68763",
    "lat": 42.517858,
    "lon": -98.582626,
    "lat_p": 2166591.951215,
    "lon_p": -213534.898668,
    "gas_price": 3.19
  },
  {
    "zipcode": "68828",
    "lat": 41.556259,
    "lon": -99.247746,
    "lat_p": 2066424.218502,
    "lon_p": -266668.611873,
    "gas_price": 3.19
  },
  {
    "zipcode": "68371",
    "lat": 40.77303,
    "lon": -97.784143,
    "lat_p": 1975621.56822,
    "lon_p": -149638.983293,
    "gas_price": 3.19
  },
  {
    "zipcode": "68348",
    "lat": 40.295686,
    "lon": -96.122112,
    "lat_p": 1920693.354025,
    "lon_p": -7195.278678,
    "gas_price": 3.19
  },
  {
    "zipcode": "68825",
    "lat": 41.273394,
    "lon": -99.957628,
    "lat_p": 2032643.243118,
    "lon_p": -327522.532817,
    "gas_price": 3.19
  },
  {
    "zipcode": "68838",
    "lat": 41.215585,
    "lon": -98.667561,
    "lat_p": 2026854.422043,
    "lon_p": -222149.202483,
    "gas_price": 3.19
  },
  {
    "zipcode": "68725",
    "lat": 42.201102,
    "lon": -98.777026,
    "lat_p": 2136730.969192,
    "lon_p": -228987.927184,
    "gas_price": 3.19
  },
  {
    "zipcode": "68401",
    "lat": 40.742339,
    "lon": -97.585595,
    "lat_p": 1971144.903009,
    "lon_p": -132156.204802,
    "gas_price": 3.19
  },
  {
    "zipcode": "68344",
    "lat": 40.571579,
    "lon": -96.395446,
    "lat_p": 1951330.365367,
    "lon_p": -32778.230457,
    "gas_price": 3.19
  },
  {
    "zipcode": "68447",
    "lat": 40.200401,
    "lon": -96.073682,
    "lat_p": 1909321.874642,
    "lon_p": -6827.153029,
    "gas_price": 3.19
  },
  {
    "zipcode": "68001",
    "lat": 41.33371,
    "lon": -96.954902,
    "lat_p": 2037020.168821,
    "lon_p": -79415.351495,
    "gas_price": 3.19
  },
  {
    "zipcode": "68853",
    "lat": 41.289723,
    "lon": -98.986224,
    "lat_p": 2032599.67168,
    "lon_p": -246384.647977,
    "gas_price": 3.19
  },
  {
    "zipcode": "68958",
    "lat": 40.527656,
    "lon": -99.503979,
    "lat_p": 1953662.468158,
    "lon_p": -294046.184843,
    "gas_price": 3.19
  },
  {
    "zipcode": "68441",
    "lat": 40.225797,
    "lon": -96.254565,
    "lat_p": 1910678.264973,
    "lon_p": -18346.698475,
    "gas_price": 3.19
  },
  {
    "zipcode": "68925",
    "lat": 40.423669,
    "lon": -98.438204,
    "lat_p": 1937881.214993,
    "lon_p": -205977.347983,
    "gas_price": 3.19
  },
  {
    "zipcode": "68973",
    "lat": 40.450119,
    "lon": -98.559624,
    "lat_p": 1939704.422762,
    "lon_p": -214710.835703,
    "gas_price": 3.19
  },
  {
    "zipcode": "68923",
    "lat": 40.368328,
    "lon": -99.473203,
    "lat_p": 1933504.585973,
    "lon_p": -292342.326529,
    "gas_price": 3.19
  },
  {
    "zipcode": "68786",
    "lat": 42.503485,
    "lon": -97.558574,
    "lat_p": 2168226.835826,
    "lon_p": -128502.758633,
    "gas_price": 3.19
  },
  {
    "zipcode": "68732",
    "lat": 42.481713,
    "lon": -96.973863,
    "lat_p": 2164689.336032,
    "lon_p": -79783.608542,
    "gas_price": 3.19
  },
  {
    "zipcode": "68755",
    "lat": 42.923264,
    "lon": -99.129601,
    "lat_p": 2216720.144362,
    "lon_p": -253632.996508,
    "gas_price": 3.19
  },
  {
    "zipcode": "68801",
    "lat": 40.949435,
    "lon": -98.292994,
    "lat_p": 1995480.727292,
    "lon_p": -189468.690933,
    "gas_price": 3.19
  },
  {
    "zipcode": "68803",
    "lat": 40.953515,
    "lon": -98.41589,
    "lat_p": 1993710.797629,
    "lon_p": -201900.694497,
    "gas_price": 3.19
  },
  {
    "zipcode": "68503",
    "lat": 40.824474,
    "lon": -96.67389,
    "lat_p": 1979634.665337,
    "lon_p": -56378.95706,
    "gas_price": 3.19
  },
  {
    "zipcode": "68824",
    "lat": 41.005355,
    "lon": -98.613989,
    "lat_p": 2004364.214296,
    "lon_p": -217467.740249,
    "gas_price": 3.19
  },
  {
    "zipcode": "68113",
    "lat": 41.117373,
    "lon": -95.908869,
    "lat_p": 2012181.270475,
    "lon_p": 8144.106907,
    "gas_price": 3.19
  },
  {
    "zipcode": "68317",
    "lat": 40.673244,
    "lon": -96.504508,
    "lat_p": 1962499.672741,
    "lon_p": -42053.247234,
    "gas_price": 3.19
  },
  {
    "zipcode": "68654",
    "lat": 41.067896,
    "lon": -97.777186,
    "lat_p": 2007259.483324,
    "lon_p": -147609.826333,
    "gas_price": 3.19
  },
  {
    "zipcode": "68620",
    "lat": 41.724488,
    "lon": -98.058076,
    "lat_p": 2082808.391586,
    "lon_p": -170964.329574,
    "gas_price": 3.19
  },
  {
    "zipcode": "68436",
    "lat": 40.43356,
    "lon": -97.744247,
    "lat_p": 1937319.316682,
    "lon_p": -146222.036921,
    "gas_price": 3.19
  },
  {
    "zipcode": "68007",
    "lat": 41.371828,
    "lon": -96.195213,
    "lat_p": 2041043.953563,
    "lon_p": -16038.502105,
    "gas_price": 3.19
  },
  {
    "zipcode": "68106",
    "lat": 41.238843,
    "lon": -96.002424,
    "lat_p": 2025924.228395,
    "lon_p": -141.453818,
    "gas_price": 3.19
  },
  {
    "zipcode": "68526",
    "lat": 40.732396,
    "lon": -96.582711,
    "lat_p": 1969298.665681,
    "lon_p": -48375.100107,
    "gas_price": 3.19
  },
  {
    "zipcode": "68352",
    "lat": 40.152541,
    "lon": -97.2193,
    "lat_p": 1905628.023093,
    "lon_p": -101266.637957,
    "gas_price": 3.19
  },
  {
    "zipcode": "68967",
    "lat": 40.252597,
    "lon": -99.630903,
    "lat_p": 1920198.927662,
    "lon_p": -301882.980637,
    "gas_price": 3.19
  },
  {
    "zipcode": "68966",
    "lat": 40.157552,
    "lon": -99.462666,
    "lat_p": 1909528.556037,
    "lon_p": -293009.736912,
    "gas_price": 3.19
  },
  {
    "zipcode": "68351",
    "lat": 40.653896,
    "lon": -97.430142,
    "lat_p": 1960803.248414,
    "lon_p": -120755.401425,
    "gas_price": 3.19
  },
  {
    "zipcode": "68152",
    "lat": 41.362821,
    "lon": -95.999962,
    "lat_p": 2040110.359837,
    "lon_p": -235.32564,
    "gas_price": 3.19
  },
  {
    "zipcode": "68118",
    "lat": 41.262991,
    "lon": -96.177188,
    "lat_p": 2028457.315882,
    "lon_p": -14732.23808,
    "gas_price": 3.19
  },
  {
    "zipcode": "68936",
    "lat": 40.316471,
    "lon": -99.778696,
    "lat_p": 1929396.003263,
    "lon_p": -317288.31067,
    "gas_price": 3.19
  },
  {
    "zipcode": "68331",
    "lat": 40.471193,
    "lon": -96.708616,
    "lat_p": 1939306.713333,
    "lon_p": -60798.54598,
    "gas_price": 3.19
  },
  {
    "zipcode": "68349",
    "lat": 40.829604,
    "lon": -96.300298,
    "lat_p": 1980480.082421,
    "lon_p": -24542.223273,
    "gas_price": 3.19
  },
  {
    "zipcode": "68347",
    "lat": 40.803473,
    "lon": -96.422751,
    "lat_p": 1977259.659748,
    "lon_p": -35650.924703,
    "gas_price": 3.19
  },
  {
    "zipcode": "68461",
    "lat": 40.766813,
    "lon": -96.514194,
    "lat_p": 1972533.06545,
    "lon_p": -43189.136094,
    "gas_price": 3.19
  },
  {
    "zipcode": "68959",
    "lat": 40.490032,
    "lon": -98.914807,
    "lat_p": 1946339.684129,
    "lon_p": -245643.29736,
    "gas_price": 3.19
  },
  {
    "zipcode": "68945",
    "lat": 40.560982,
    "lon": -98.773268,
    "lat_p": 1952354.423047,
    "lon_p": -232694.946165,
    "gas_price": 3.19
  },
  {
    "zipcode": "68972",
    "lat": 40.103691,
    "lon": -98.80257,
    "lat_p": 1903643.954689,
    "lon_p": -235066.164453,
    "gas_price": 3.19
  },
  {
    "zipcode": "68337",
    "lat": 40.095057,
    "lon": -95.834174,
    "lat_p": 1896797.816979,
    "lon_p": 15821.721587,
    "gas_price": 3.19
  },
  {
    "zipcode": "68437",
    "lat": 40.251322,
    "lon": -95.635338,
    "lat_p": 1915197.580885,
    "lon_p": 30008.736049,
    "gas_price": 3.19
  },
  {
    "zipcode": "68952",
    "lat": 40.084343,
    "lon": -98.67579,
    "lat_p": 1900106.932567,
    "lon_p": -226910.445763,
    "gas_price": 3.19
  },
  {
    "zipcode": "68653",
    "lat": 41.555537,
    "lon": -97.488828,
    "lat_p": 2061201.829995,
    "lon_p": -122842.377903,
    "gas_price": 3.19
  },
  {
    "zipcode": "68462",
    "lat": 40.948026,
    "lon": -96.528019,
    "lat_p": 1994525.913397,
    "lon_p": -44619.815947,
    "gas_price": 3.19
  },
  {
    "zipcode": "68974",
    "lat": 40.132357,
    "lon": -97.864533,
    "lat_p": 1903437.834186,
    "lon_p": -156129.387803,
    "gas_price": 3.19
  },
  {
    "zipcode": "68660",
    "lat": 41.573971,
    "lon": -97.867959,
    "lat_p": 2065778.012426,
    "lon_p": -154292.309238,
    "gas_price": 3.19
  },
  {
    "zipcode": "68465",
    "lat": 40.492506,
    "lon": -97.019893,
    "lat_p": 1942806.667042,
    "lon_p": -86289.105933,
    "gas_price": 3.19
  },
  {
    "zipcode": "68655",
    "lat": 41.648809,
    "lon": -98.262212,
    "lat_p": 2074354.307358,
    "lon_p": -185441.125843,
    "gas_price": 3.19
  },
  {
    "zipcode": "68023",
    "lat": 41.461842,
    "lon": -96.02214,
    "lat_p": 2051383.884193,
    "lon_p": -2264.172467,
    "gas_price": 3.19
  },
  {
    "zipcode": "68424",
    "lat": 40.301106,
    "lon": -97.018184,
    "lat_p": 1919240.350857,
    "lon_p": -86768.997521,
    "gas_price": 3.19
  },
  {
    "zipcode": "68847",
    "lat": 40.734537,
    "lon": -99.022713,
    "lat_p": 1973372.496574,
    "lon_p": -252794.533993,
    "gas_price": 3.19
  },
  {
    "zipcode": "68442",
    "lat": 40.239002,
    "lon": -95.772913,
    "lat_p": 1913079.475408,
    "lon_p": 16556.047401,
    "gas_price": 3.19
  },
  {
    "zipcode": "68841",
    "lat": 40.763154,
    "lon": -98.166759,
    "lat_p": 1974133.371536,
    "lon_p": -182343.819654,
    "gas_price": 3.19
  },
  {
    "zipcode": "68429",
    "lat": 40.064036,
    "lon": -97.374334,
    "lat_p": 1894126.769738,
    "lon_p": -114161.642014,
    "gas_price": 3.19
  },
  {
    "zipcode": "68843",
    "lat": 40.903293,
    "lon": -97.880197,
    "lat_p": 1989529.364278,
    "lon_p": -156564.640697,
    "gas_price": 3.19
  },
  {
    "zipcode": "68514",
    "lat": 40.934063,
    "lon": -96.650743,
    "lat_p": 1990910.3616,
    "lon_p": -54546.169058,
    "gas_price": 3.19
  },
  {
    "zipcode": "68133",
    "lat": 41.117496,
    "lon": -96.002901,
    "lat_p": 2012196.396869,
    "lon_p": -395.405149,
    "gas_price": 3.19
  },
  {
    "zipcode": "68372",
    "lat": 40.604979,
    "lon": -96.605386,
    "lat_p": 1954763.95071,
    "lon_p": -51307.341304,
    "gas_price": 3.19
  },
  {
    "zipcode": "68964",
    "lat": 40.235402,
    "lon": -97.902042,
    "lat_p": 1914831.11215,
    "lon_p": -161140.982382,
    "gas_price": 3.19
  },
  {
    "zipcode": "68434",
    "lat": 40.909453,
    "lon": -97.116789,
    "lat_p": 1990547.244026,
    "lon_p": -94394.458287,
    "gas_price": 3.19
  },
  {
    "zipcode": "68138",
    "lat": 41.156589,
    "lon": -96.138897,
    "lat_p": 2016701.720855,
    "lon_p": -11600.405182,
    "gas_price": 3.19
  },
  {
    "zipcode": "68154",
    "lat": 41.26407,
    "lon": -96.116676,
    "lat_p": 2028093.312232,
    "lon_p": -8136.995894,
    "gas_price": 3.19
  },
  {
    "zipcode": "68865",
    "lat": 40.893353,
    "lon": -98.187051,
    "lat_p": 1990402.006148,
    "lon_p": -182131.285935,
    "gas_price": 3.19
  },
  {
    "zipcode": "68713",
    "lat": 42.540166,
    "lon": -98.97209,
    "lat_p": 2176865.632416,
    "lon_p": -237619.358981,
    "gas_price": 3.19
  },
  {
    "zipcode": "68780",
    "lat": 42.64601,
    "lon": -99.140667,
    "lat_p": 2186829.983426,
    "lon_p": -255740.906239,
    "gas_price": 3.19
  },
  {
    "zipcode": "68879",
    "lat": 41.873866,
    "lon": -99.500567,
    "lat_p": 2102116.652508,
    "lon_p": -287935.017174,
    "gas_price": 3.19
  },
  {
    "zipcode": "68842",
    "lat": 41.580668,
    "lon": -98.534505,
    "lat_p": 2069515.94207,
    "lon_p": -209548.905924,
    "gas_price": 3.19
  },
  {
    "zipcode": "68862",
    "lat": 41.603522,
    "lon": -98.938521,
    "lat_p": 2068569.522399,
    "lon_p": -245125.724438,
    "gas_price": 3.19
  },
  {
    "zipcode": "68856",
    "lat": 41.501662,
    "lon": -99.816896,
    "lat_p": 2061633.957823,
    "lon_p": -310658.168554,
    "gas_price": 3.19
  },
  {
    "zipcode": "68852",
    "lat": 41.167137,
    "lon": -99.146287,
    "lat_p": 2022445.604683,
    "lon_p": -261205.759728,
    "gas_price": 3.19
  },
  {
    "zipcode": "68858",
    "lat": 40.961697,
    "lon": -99.377946,
    "lat_p": 1999450.382665,
    "lon_p": -281991.724732,
    "gas_price": 3.19
  },
  {
    "zipcode": "68624",
    "lat": 41.349745,
    "lon": -97.228628,
    "lat_p": 2038225.711401,
    "lon_p": -102490.788225,
    "gas_price": 3.19
  },
  {
    "zipcode": "68777",
    "lat": 42.8608,
    "lon": -98.68502,
    "lat_p": 2209719.394823,
    "lon_p": -217997.839638,
    "gas_price": 3.19
  },
  {
    "zipcode": "68418",
    "lat": 40.695654,
    "lon": -96.384366,
    "lat_p": 1965870.852788,
    "lon_p": -32449.712224,
    "gas_price": 3.19
  },
  {
    "zipcode": "68014",
    "lat": 41.282193,
    "lon": -96.964569,
    "lat_p": 2031391.272607,
    "lon_p": -79554.846419,
    "gas_price": 3.19
  },
  {
    "zipcode": "68976",
    "lat": 40.602316,
    "lon": -99.709135,
    "lat_p": 1959633.29508,
    "lon_p": -311214.33873,
    "gas_price": 3.19
  },
  {
    "zipcode": "68329",
    "lat": 40.500895,
    "lon": -96.167734,
    "lat_p": 1943956.561366,
    "lon_p": -14345.937215,
    "gas_price": 3.19
  },
  {
    "zipcode": "68873",
    "lat": 41.246912,
    "lon": -98.451514,
    "lat_p": 2029651.10316,
    "lon_p": -206876.698026,
    "gas_price": 3.19
  },
  {
    "zipcode": "68016",
    "lat": 41.025193,
    "lon": -96.106303,
    "lat_p": 2001966.549882,
    "lon_p": -8893.426593,
    "gas_price": 3.19
  },
  {
    "zipcode": "68747",
    "lat": 42.393982,
    "lon": -97.488714,
    "lat_p": 2155210.428341,
    "lon_p": -122259.264279,
    "gas_price": 3.19
  },
  {
    "zipcode": "68710",
    "lat": 42.439008,
    "lon": -96.847832,
    "lat_p": 2160249.803495,
    "lon_p": -68614.744346,
    "gas_price": 3.19
  },
  {
    "zipcode": "68727",
    "lat": 42.511588,
    "lon": -97.205968,
    "lat_p": 2169413.276717,
    "lon_p": -98332.045612,
    "gas_price": 3.19
  },
  {
    "zipcode": "68751",
    "lat": 42.69043,
    "lon": -96.981426,
    "lat_p": 2188640.080472,
    "lon_p": -79976.588686,
    "gas_price": 3.19
  },
  {
    "zipcode": "68810",
    "lat": 40.862373,
    "lon": -98.467496,
    "lat_p": 1985750.53487,
    "lon_p": -206244.901624,
    "gas_price": 3.19
  },
  {
    "zipcode": "68505",
    "lat": 40.824398,
    "lon": -96.615664,
    "lat_p": 1979483.254654,
    "lon_p": -51516.991864,
    "gas_price": 3.19
  },
  {
    "zipcode": "68588",
    "lat": 40.824921,
    "lon": -96.696429,
    "lat_p": 1979551.725318,
    "lon_p": -58233.502954,
    "gas_price": 3.19
  },
  {
    "zipcode": "68107",
    "lat": 41.208884,
    "lon": -95.951746,
    "lat_p": 2022644.332476,
    "lon_p": 4046.271541,
    "gas_price": 3.19
  },
  {
    "zipcode": "68104",
    "lat": 41.295238,
    "lon": -96.001078,
    "lat_p": 2032271.211162,
    "lon_p": 16.782638,
    "gas_price": 3.19
  },
  {
    "zipcode": "68124",
    "lat": 41.235141,
    "lon": -96.0522,
    "lat_p": 2025321.148768,
    "lon_p": -4381.572335,
    "gas_price": 3.19
  },
  {
    "zipcode": "68651",
    "lat": 41.22441,
    "lon": -97.574733,
    "lat_p": 2026524.307106,
    "lon_p": -131342.97031,
    "gas_price": 3.19
  },
  {
    "zipcode": "68957",
    "lat": 40.267395,
    "lon": -98.241713,
    "lat_p": 1918830.185413,
    "lon_p": -188557.306499,
    "gas_price": 3.19
  },
  {
    "zipcode": "68977",
    "lat": 40.066952,
    "lon": -99.630522,
    "lat_p": 1902175.30387,
    "lon_p": -306830.975628,
    "gas_price": 3.19
  },
  {
    "zipcode": "68067",
    "lat": 42.151901,
    "lon": -96.486049,
    "lat_p": 2128762.002419,
    "lon_p": -39196.717141,
    "gas_price": 3.19
  },
  {
    "zipcode": "68629",
    "lat": 41.713267,
    "lon": -97.12935,
    "lat_p": 2081079.479403,
    "lon_p": -94669.00797,
    "gas_price": 3.19
  },
  {
    "zipcode": "68939",
    "lat": 40.109736,
    "lon": -98.961741,
    "lat_p": 1905658.93828,
    "lon_p": -245996.519794,
    "gas_price": 3.19
  },
  {
    "zipcode": "68960",
    "lat": 40.085501,
    "lon": -99.138636,
    "lat_p": 1901425.798598,
    "lon_p": -263878.166785,
    "gas_price": 3.19
  },
  {
    "zipcode": "68466",
    "lat": 40.071159,
    "lon": -96.637698,
    "lat_p": 1895033.856362,
    "lon_p": -53536.189025,
    "gas_price": 3.19
  },
  {
    "zipcode": "68022",
    "lat": 41.277422,
    "lon": -96.245581,
    "lat_p": 2030034.815559,
    "lon_p": -19631.69454,
    "gas_price": 3.19
  },
  {
    "zipcode": "68440",
    "lat": 40.052645,
    "lon": -97.011657,
    "lat_p": 1892489.81245,
    "lon_p": -85080.475206,
    "gas_price": 3.19
  },
  {
    "zipcode": "68402",
    "lat": 40.908279,
    "lon": -96.85711,
    "lat_p": 1989238.951644,
    "lon_p": -71276.995571,
    "gas_price": 3.19
  },
  {
    "zipcode": "68531",
    "lat": 40.902122,
    "lon": -96.714128,
    "lat_p": 1988373.856684,
    "lon_p": -59361.646639,
    "gas_price": 3.19
  },
  {
    "zipcode": "68642",
    "lat": 41.687163,
    "lon": -97.512314,
    "lat_p": 2077129.371727,
    "lon_p": -123030.612726,
    "gas_price": 3.19
  },
  {
    "zipcode": "68030",
    "lat": 42.318341,
    "lon": -96.450544,
    "lat_p": 2147198.81519,
    "lon_p": -36182.646298,
    "gas_price": 3.19
  },
  {
    "zipcode": "68527",
    "lat": 40.845736,
    "lon": -96.517538,
    "lat_p": 1982097.553924,
    "lon_p": -42989.119638,
    "gas_price": 3.19
  },
  {
    "zipcode": "68933",
    "lat": 40.517872,
    "lon": -98.042124,
    "lat_p": 1947587.682316,
    "lon_p": -173145.907811,
    "gas_price": 3.19
  },
  {
    "zipcode": "68019",
    "lat": 41.779604,
    "lon": -96.373256,
    "lat_p": 2086922.516612,
    "lon_p": -31864.763504,
    "gas_price": 3.19
  },
  {
    "zipcode": "68644",
    "lat": 41.707823,
    "lon": -97.675799,
    "lat_p": 2080528.291441,
    "lon_p": -136485.838011,
    "gas_price": 3.19
  },
  {
    "zipcode": "68464",
    "lat": 40.422295,
    "lon": -97.195473,
    "lat_p": 1935965.339816,
    "lon_p": -101579.252508,
    "gas_price": 3.19
  },
  {
    "zipcode": "68669",
    "lat": 41.077893,
    "lon": -97.23612,
    "lat_p": 2009340.050362,
    "lon_p": -100454.483121,
    "gas_price": 3.19
  },
  {
    "zipcode": "68042",
    "lat": 41.094221,
    "lon": -96.436738,
    "lat_p": 2009447.467471,
    "lon_p": -36117.961801,
    "gas_price": 3.19
  },
  {
    "zipcode": "68882",
    "lat": 41.423645,
    "lon": -98.403681,
    "lat_p": 2047532.369805,
    "lon_p": -201987.213942,
    "gas_price": 3.19
  },
  {
    "zipcode": "68814",
    "lat": 41.308521,
    "lon": -99.410248,
    "lat_p": 2039350.669007,
    "lon_p": -280028.03081,
    "gas_price": 3.19
  },
  {
    "zipcode": "68837",
    "lat": 41.661417,
    "lon": -99.060634,
    "lat_p": 2076099.360647,
    "lon_p": -254319.517385,
    "gas_price": 3.19
  },
  {
    "zipcode": "68446",
    "lat": 40.650027,
    "lon": -96.175349,
    "lat_p": 1959450.827035,
    "lon_p": -12759.117003,
    "gas_price": 3.19
  },
  {
    "zipcode": "68742",
    "lat": 42.357133,
    "lon": -98.514594,
    "lat_p": 2153438.180182,
    "lon_p": -205798.87986,
    "gas_price": 3.19
  },
  {
    "zipcode": "68711",
    "lat": 42.203375,
    "lon": -99.024182,
    "lat_p": 2141342.620008,
    "lon_p": -255604.349062,
    "gas_price": 3.19
  },
  {
    "zipcode": "68746",
    "lat": 42.807148,
    "lon": -98.435353,
    "lat_p": 2204988.092912,
    "lon_p": -197370.038732,
    "gas_price": 3.19
  },
  {
    "zipcode": "68443",
    "lat": 40.456258,
    "lon": -96.367596,
    "lat_p": 1937263.094408,
    "lon_p": -31017.195534,
    "gas_price": 3.19
  },
  {
    "zipcode": "68323",
    "lat": 40.131928,
    "lon": -96.370302,
    "lat_p": 1900995.585285,
    "lon_p": -31989.343376,
    "gas_price": 3.19
  },
  {
    "zipcode": "68626",
    "lat": 41.168205,
    "lon": -96.992109,
    "lat_p": 2018483.92696,
    "lon_p": -81225.288385,
    "gas_price": 3.19
  },
  {
    "zipcode": "68875",
    "lat": 41.513275,
    "lon": -98.681987,
    "lat_p": 2060006.908561,
    "lon_p": -223080.401729,
    "gas_price": 3.19
  },
  {
    "zipcode": "68950",
    "lat": 40.455848,
    "lon": -98.66413,
    "lat_p": 1939987.219116,
    "lon_p": -224273.679121,
    "gas_price": 3.19
  },
  {
    "zipcode": "68634",
    "lat": 41.390754,
    "lon": -97.506616,
    "lat_p": 2043742.059371,
    "lon_p": -124695.992072,
    "gas_price": 3.19
  },
  {
    "zipcode": "68836",
    "lat": 40.707049,
    "lon": -99.378612,
    "lat_p": 1972053.795904,
    "lon_p": -282248.09142,
    "gas_price": 3.19
  },
  {
    "zipcode": "68881",
    "lat": 41.434669,
    "lon": -99.359595,
    "lat_p": 2052478.965812,
    "lon_p": -279163.920487,
    "gas_price": 3.19
  },
  {
    "zipcode": "68739",
    "lat": 42.628408,
    "lon": -97.262705,
    "lat_p": 2182569.614231,
    "lon_p": -102742.768295,
    "gas_price": 3.19
  },
  {
    "zipcode": "68757",
    "lat": 42.652413,
    "lon": -96.925504,
    "lat_p": 2184021.934345,
    "lon_p": -75160.28267,
    "gas_price": 3.19
  },
  {
    "zipcode": "68730",
    "lat": 42.766801,
    "lon": -97.534756,
    "lat_p": 2194588.428507,
    "lon_p": -124112.648454,
    "gas_price": 3.19
  },
  {
    "zipcode": "68749",
    "lat": 42.460326,
    "lon": -97.475323,
    "lat_p": 2163365.551708,
    "lon_p": -120563.963358,
    "gas_price": 3.19
  },
  {
    "zipcode": "68507",
    "lat": 40.859487,
    "lon": -96.61172,
    "lat_p": 1983466.274056,
    "lon_p": -50649.703505,
    "gas_price": 3.19
  },
  {
    "zipcode": "68504",
    "lat": 40.854506,
    "lon": -96.660983,
    "lat_p": 1982511.105152,
    "lon_p": -55390.395569,
    "gas_price": 3.19
  },
  {
    "zipcode": "68110",
    "lat": 41.298827,
    "lon": -95.911155,
    "lat_p": 2032037.653526,
    "lon_p": 9315.663201,
    "gas_price": 3.19
  },
  {
    "zipcode": "68831",
    "lat": 41.109357,
    "lon": -98.546602,
    "lat_p": 2014450.331066,
    "lon_p": -212943.679737,
    "gas_price": 3.19
  },
  {
    "zipcode": "68883",
    "lat": 40.818179,
    "lon": -98.585591,
    "lat_p": 1981162.79467,
    "lon_p": -215738.752153,
    "gas_price": 3.19
  },
  {
    "zipcode": "68102",
    "lat": 41.262299,
    "lon": -95.932567,
    "lat_p": 2028367.637048,
    "lon_p": 5523.767322,
    "gas_price": 3.19
  },
  {
    "zipcode": "68901",
    "lat": 40.590897,
    "lon": -98.365983,
    "lat_p": 1956391.855681,
    "lon_p": -197981.490463,
    "gas_price": 3.19
  },
  {
    "zipcode": "68516",
    "lat": 40.734926,
    "lon": -96.642798,
    "lat_p": 1969326.145392,
    "lon_p": -53977.113498,
    "gas_price": 3.19
  },
  {
    "zipcode": "68776",
    "lat": 42.460106,
    "lon": -96.444193,
    "lat_p": 2161741.652279,
    "lon_p": -36896.446817,
    "gas_price": 3.19
  },
  {
    "zipcode": "68339",
    "lat": 40.732132,
    "lon": -96.866971,
    "lat_p": 1969618.964382,
    "lon_p": -71525.54381,
    "gas_price": 3.19
  },
  {
    "zipcode": "68368",
    "lat": 40.555979,
    "lon": -96.816667,
    "lat_p": 1950741.468899,
    "lon_p": -69884.238981,
    "gas_price": 3.19
  },
  {
    "zipcode": "68114",
    "lat": 41.263181,
    "lon": -96.05209,
    "lat_p": 2028405.998193,
    "lon_p": -4160.578356,
    "gas_price": 3.19
  },
  {
    "zipcode": "68301",
    "lat": 40.468402,
    "lon": -96.522485,
    "lat_p": 1941548.966272,
    "lon_p": -43924.968864,
    "gas_price": 3.19
  },
  {
    "zipcode": "68659",
    "lat": 41.543858,
    "lon": -96.944346,
    "lat_p": 2060143.404196,
    "lon_p": -79017.991806,
    "gas_price": 3.19
  },
  {
    "zipcode": "68641",
    "lat": 41.734419,
    "lon": -97.008263,
    "lat_p": 2080946.443186,
    "lon_p": -83546.773936,
    "gas_price": 3.19
  },
  {
    "zipcode": "68048",
    "lat": 40.983041,
    "lon": -95.934454,
    "lat_p": 1995455.694038,
    "lon_p": 5259.375462,
    "gas_price": 3.19
  },
  {
    "zipcode": "68328",
    "lat": 40.476933,
    "lon": -96.838414,
    "lat_p": 1940639.939317,
    "lon_p": -70335.917312,
    "gas_price": 3.19
  },
  {
    "zipcode": "68064",
    "lat": 41.349232,
    "lon": -96.355434,
    "lat_p": 2037808.064186,
    "lon_p": -29016.268845,
    "gas_price": 3.19
  },
  {
    "zipcode": "68621",
    "lat": 41.489644,
    "lon": -96.639147,
    "lat_p": 2054830.25817,
    "lon_p": -52676.697466,
    "gas_price": 3.19
  },
  {
    "zipcode": "68137",
    "lat": 41.205941,
    "lon": -96.119244,
    "lat_p": 2022259.553622,
    "lon_p": -9964.79934,
    "gas_price": 3.19
  },
  {
    "zipcode": "68930",
    "lat": 40.285079,
    "lon": -98.418488,
    "lat_p": 1921719.986765,
    "lon_p": -205169.486138,
    "gas_price": 3.19
  },
  {
    "zipcode": "68638",
    "lat": 41.36845,
    "lon": -97.989785,
    "lat_p": 2044058.516469,
    "lon_p": -166516.471011,
    "gas_price": 3.19
  },
  {
    "zipcode": "68010",
    "lat": 41.256147,
    "lon": -96.133516,
    "lat_p": 2027629.485053,
    "lon_p": -11135.583548,
    "gas_price": 3.19
  },
  {
    "zipcode": "68409",
    "lat": 40.909081,
    "lon": -95.950753,
    "lat_p": 1988640.326318,
    "lon_p": 4417.769422,
    "gas_price": 3.19
  },
  {
    "zipcode": "68935",
    "lat": 40.380545,
    "lon": -97.958593,
    "lat_p": 1932435.755632,
    "lon_p": -163905.138422,
    "gas_price": 3.19
  },
  {
    "zipcode": "68627",
    "lat": 41.544451,
    "lon": -98.170438,
    "lat_p": 2061796.075344,
    "lon_p": -179791.127293,
    "gas_price": 3.19
  },
  {
    "zipcode": "68758",
    "lat": 41.782875,
    "lon": -97.788628,
    "lat_p": 2086458.279102,
    "lon_p": -148063.542686,
    "gas_price": 3.19
  },
  {
    "zipcode": "68941",
    "lat": 40.468823,
    "lon": -98.267895,
    "lat_p": 1939971.539074,
    "lon_p": -190783.988494,
    "gas_price": 3.19
  },
  {
    "zipcode": "68423",
    "lat": 40.801082,
    "lon": -96.951197,
    "lat_p": 1977715.161599,
    "lon_p": -80195.480338,
    "gas_price": 3.19
  },
  {
    "zipcode": "68326",
    "lat": 40.285671,
    "lon": -97.682419,
    "lat_p": 1920407.777194,
    "lon_p": -141557.536953,
    "gas_price": 3.19
  },
  {
    "zipcode": "68340",
    "lat": 40.125202,
    "lon": -97.741207,
    "lat_p": 1901165.875571,
    "lon_p": -148291.533314,
    "gas_price": 3.19
  },
  {
    "zipcode": "68063",
    "lat": 41.721196,
    "lon": -96.493462,
    "lat_p": 2079817.603274,
    "lon_p": -40679.070972,
    "gas_price": 3.19
  },
  {
    "zipcode": "68038",
    "lat": 41.954575,
    "lon": -96.443202,
    "lat_p": 2106433.970123,
    "lon_p": -36374.277284,
    "gas_price": 3.19
  },
  {
    "zipcode": "68944",
    "lat": 40.637412,
    "lon": -98.094898,
    "lat_p": 1961520.126833,
    "lon_p": -175219.32128,
    "gas_price": 3.19
  },
  {
    "zipcode": "68322",
    "lat": 40.334609,
    "lon": -97.553547,
    "lat_p": 1924822.692337,
    "lon_p": -129590.018637,
    "gas_price": 3.19
  },
  {
    "zipcode": "68182",
    "lat": 41.257745,
    "lon": -96.010674,
    "lat_p": 2027821.718264,
    "lon_p": -874.679685,
    "gas_price": 3.19
  },
  {
    "zipcode": "68740",
    "lat": 42.145591,
    "lon": -97.292423,
    "lat_p": 2129901.451539,
    "lon_p": -107532.86986,
    "gas_price": 3.19
  },
  {
    "zipcode": "68070",
    "lat": 41.192405,
    "lon": -96.799706,
    "lat_p": 2020888.989274,
    "lon_p": -67645.282962,
    "gas_price": 3.19
  },
  {
    "zipcode": "68321",
    "lat": 40.394891,
    "lon": -95.693674,
    "lat_p": 1930092.251753,
    "lon_p": 25791.595644,
    "gas_price": 3.19
  },
  {
    "zipcode": "68648",
    "lat": 41.404822,
    "lon": -96.789493,
    "lat_p": 2044052.365941,
    "lon_p": -66372.525211,
    "gas_price": 3.19
  },
  {
    "zipcode": "68467",
    "lat": 40.865242,
    "lon": -97.597777,
    "lat_p": 1985835.836489,
    "lon_p": -135105.806139,
    "gas_price": 3.19
  },
  {
    "zipcode": "68870",
    "lat": 40.845298,
    "lon": -99.158363,
    "lat_p": 1986022.744477,
    "lon_p": -265220.344402,
    "gas_price": 3.19
  },
  {
    "zipcode": "68036",
    "lat": 41.390311,
    "lon": -96.950838,
    "lat_p": 2042940.854801,
    "lon_p": -80153.22565,
    "gas_price": 3.19
  },
  {
    "zipcode": "68450",
    "lat": 40.361968,
    "lon": -96.223866,
    "lat_p": 1926912.826944,
    "lon_p": -21511.290052,
    "gas_price": 3.19
  },
  {
    "zipcode": "68764",
    "lat": 42.398745,
    "lon": -98.231779,
    "lat_p": 2158656.42318,
    "lon_p": -183370.489204,
    "gas_price": 3.19
  },
  {
    "zipcode": "68821",
    "lat": 42.001782,
    "lon": -99.816187,
    "lat_p": 2117266.834887,
    "lon_p": -313537.586937,
    "gas_price": 3.19
  },
  {
    "zipcode": "68756",
    "lat": 42.185421,
    "lon": -97.979869,
    "lat_p": 2133150.575143,
    "lon_p": -161682.862211,
    "gas_price": 3.19
  },
  {
    "zipcode": "68761",
    "lat": 42.022803,
    "lon": -97.960067,
    "lat_p": 2115278.212283,
    "lon_p": -161966.01702,
    "gas_price": 3.19
  },
  {
    "zipcode": "68940",
    "lat": 40.538108,
    "lon": -99.25085,
    "lat_p": 1952114.758169,
    "lon_p": -273797.52863,
    "gas_price": 3.19
  },
  {
    "zipcode": "68844",
    "lat": 41.056575,
    "lon": -99.059333,
    "lat_p": 2009020.464489,
    "lon_p": -255447.846688,
    "gas_price": 3.19
  },
  {
    "zipcode": "68924",
    "lat": 40.495501,
    "lon": -99.124672,
    "lat_p": 1946825.08167,
    "lon_p": -260783.602321,
    "gas_price": 3.19
  },
  {
    "zipcode": "68846",
    "lat": 41.065001,
    "lon": -97.885316,
    "lat_p": 2007399.270988,
    "lon_p": -157185.038081,
    "gas_price": 3.19
  },
  {
    "zipcode": "68729",
    "lat": 42.474813,
    "lon": -97.907872,
    "lat_p": 2165405.151227,
    "lon_p": -157341.38747,
    "gas_price": 3.19
  },
  {
    "zipcode": "68718",
    "lat": 42.661814,
    "lon": -97.698374,
    "lat_p": 2188353.078103,
    "lon_p": -137359.871922,
    "gas_price": 3.19
  },
  {
    "zipcode": "68304",
    "lat": 40.889768,
    "lon": -96.387791,
    "lat_p": 1986939.779459,
    "lon_p": -31724.581039,
    "gas_price": 3.19
  },
  {
    "zipcode": "68058",
    "lat": 41.008441,
    "lon": -96.248215,
    "lat_p": 1999596.357187,
    "lon_p": -20078.366965,
    "gas_price": 3.19
  },
  {
    "zipcode": "68622",
    "lat": 41.922135,
    "lon": -98.532998,
    "lat_p": 2104124.466231,
    "lon_p": -205838.169371,
    "gas_price": 3.19
  },
  {
    "zipcode": "68723",
    "lat": 42.287578,
    "lon": -97.214577,
    "lat_p": 2143609.784472,
    "lon_p": -99362.687499,
    "gas_price": 3.19
  },
  {
    "zipcode": "68728",
    "lat": 42.380858,
    "lon": -96.936347,
    "lat_p": 2152739.306882,
    "lon_p": -75368.280785,
    "gas_price": 3.19
  },
  {
    "zipcode": "68736",
    "lat": 42.744834,
    "lon": -97.371384,
    "lat_p": 2195640.34866,
    "lon_p": -111297.31713,
    "gas_price": 3.19
  },
  {
    "zipcode": "68717",
    "lat": 42.389594,
    "lon": -97.219216,
    "lat_p": 2156545.329401,
    "lon_p": -100004.263927,
    "gas_price": 3.19
  },
  {
    "zipcode": "68760",
    "lat": 42.766204,
    "lon": -98.038193,
    "lat_p": 2198674.60021,
    "lon_p": -177244.05178,
    "gas_price": 3.19
  },
  {
    "zipcode": "68956",
    "lat": 40.630871,
    "lon": -98.689088,
    "lat_p": 1960060.567938,
    "lon_p": -223710.142438,
    "gas_price": 3.19
  },
  {
    "zipcode": "68832",
    "lat": 40.769621,
    "lon": -98.366099,
    "lat_p": 1977318.410122,
    "lon_p": -195804.268106,
    "gas_price": 3.19
  },
  {
    "zipcode": "68521",
    "lat": 40.861803,
    "lon": -96.715129,
    "lat_p": 1983736.588876,
    "lon_p": -59580.977264,
    "gas_price": 3.19
  },
  {
    "zipcode": "68522",
    "lat": 40.789411,
    "lon": -96.762121,
    "lat_p": 1975842.716753,
    "lon_p": -63638.757969,
    "gas_price": 3.19
  },
  {
    "zipcode": "68404",
    "lat": 40.618982,
    "lon": -96.755644,
    "lat_p": 1956556.631799,
    "lon_p": -63566.501004,
    "gas_price": 3.19
  },
  {
    "zipcode": "68333",
    "lat": 40.621269,
    "lon": -96.949043,
    "lat_p": 1956599.435678,
    "lon_p": -79049.722518,
    "gas_price": 3.19
  },
  {
    "zipcode": "68701",
    "lat": 42.020212,
    "lon": -97.440985,
    "lat_p": 2113876.846761,
    "lon_p": -116534.271956,
    "gas_price": 3.19
  },
  {
    "zipcode": "68961",
    "lat": 40.206776,
    "lon": -98.034992,
    "lat_p": 1913069.725786,
    "lon_p": -171564.894753,
    "gas_price": 3.19
  },
  {
    "zipcode": "68781",
    "lat": 42.027336,
    "lon": -97.845619,
    "lat_p": 2115189.360875,
    "lon_p": -152097.184629,
    "gas_price": 3.19
  },
  {
    "zipcode": "68314",
    "lat": 41.016417,
    "lon": -97.024745,
    "lat_p": 2000993.356954,
    "lon_p": -85960.764885,
    "gas_price": 3.19
  },
  {
    "zipcode": "68752",
    "lat": 42.022553,
    "lon": -97.715384,
    "lat_p": 2115770.432753,
    "lon_p": -142572.850528,
    "gas_price": 3.19
  },
  {
    "zipcode": "68937",
    "lat": 40.572575,
    "lon": -99.854929,
    "lat_p": 1959533.879644,
    "lon_p": -324646.516333,
    "gas_price": 3.19
  },
  {
    "zipcode": "68456",
    "lat": 40.912727,
    "lon": -97.31007,
    "lat_p": 1990392.697827,
    "lon_p": -110321.666921,
    "gas_price": 3.19
  },
  {
    "zipcode": "68453",
    "lat": 40.407731,
    "lon": -97.334549,
    "lat_p": 1933545.050116,
    "lon_p": -112755.088707,
    "gas_price": 3.19
  },
  {
    "zipcode": "68128",
    "lat": 41.179737,
    "lon": -96.070799,
    "lat_p": 2018318.319462,
    "lon_p": -5893.182669,
    "gas_price": 3.19
  },
  {
    "zipcode": "68136",
    "lat": 41.169312,
    "lon": -96.187813,
    "lat_p": 2017911.707442,
    "lon_p": -15633.417188,
    "gas_price": 3.19
  },
  {
    "zipcode": "68144",
    "lat": 41.234728,
    "lon": -96.119142,
    "lat_p": 2025122.859213,
    "lon_p": -9939.694831,
    "gas_price": 3.19
  },
  {
    "zipcode": "68342",
    "lat": 40.103415,
    "lon": -96.944931,
    "lat_p": 1898112.354213,
    "lon_p": -79847.297838,
    "gas_price": 3.19
  },
  {
    "zipcode": "68926",
    "lat": 40.093124,
    "lon": -99.851418,
    "lat_p": 1905857.594351,
    "lon_p": -325607.423705,
    "gas_price": 3.19
  },
  {
    "zipcode": "68971",
    "lat": 40.119265,
    "lon": -99.244784,
    "lat_p": 1904816.411374,
    "lon_p": -274898.454976,
    "gas_price": 3.19
  },
  {
    "zipcode": "68979",
    "lat": 40.597115,
    "lon": -97.853172,
    "lat_p": 1953777.141397,
    "lon_p": -156288.72508,
    "gas_price": 3.19
  },
  {
    "zipcode": "68134",
    "lat": 41.297775,
    "lon": -96.050317,
    "lat_p": 2032355.13879,
    "lon_p": -4258.857109,
    "gas_price": 3.19
  },
  {
    "zipcode": "68932",
    "lat": 40.302589,
    "lon": -98.738484,
    "lat_p": 1923738.972091,
    "lon_p": -230555.364877,
    "gas_price": 3.19
  },
  {
    "zipcode": "68444",
    "lat": 40.41117,
    "lon": -97.584712,
    "lat_p": 1934670.083514,
    "lon_p": -134296.641251,
    "gas_price": 3.19
  },
  {
    "zipcode": "68601",
    "lat": 41.452029,
    "lon": -97.394899,
    "lat_p": 2053079.873856,
    "lon_p": -112608.964361,
    "gas_price": 3.19
  },
  {
    "zipcode": "68366",
    "lat": 40.982184,
    "lon": -96.442251,
    "lat_p": 1996217.284304,
    "lon_p": -35554.907462,
    "gas_price": 3.19
  },
  {
    "zipcode": "68029",
    "lat": 41.658726,
    "lon": -96.274116,
    "lat_p": 2071862.922237,
    "lon_p": -23976.652998,
    "gas_price": 3.19
  },
  {
    "zipcode": "68863",
    "lat": 40.766185,
    "lon": -99.525186,
    "lat_p": 1978008.866091,
    "lon_p": -295572.316017,
    "gas_price": 3.19
  },
  {
    "zipcode": "68981",
    "lat": 40.286005,
    "lon": -98.892393,
    "lat_p": 1921727.820121,
    "lon_p": -245699.826486,
    "gas_price": 3.19
  },
  {
    "zipcode": "68826",
    "lat": 41.163346,
    "lon": -98.019131,
    "lat_p": 2017772.036832,
    "lon_p": -165912.554738,
    "gas_price": 3.19
  },
  {
    "zipcode": "68430",
    "lat": 40.665999,
    "lon": -96.660104,
    "lat_p": 1961647.532612,
    "lon_p": -54548.918931,
    "gas_price": 3.19
  },
  {
    "zipcode": "68031",
    "lat": 41.640385,
    "lon": -96.530487,
    "lat_p": 2070033.450489,
    "lon_p": -42297.08892,
    "gas_price": 3.19
  },
  {
    "zipcode": "68072",
    "lat": 41.610126,
    "lon": -96.504696,
    "lat_p": 2067366.601409,
    "lon_p": -41757.417274,
    "gas_price": 3.19
  },
  {
    "zipcode": "68532",
    "lat": 40.795421,
    "lon": -96.843344,
    "lat_p": 1976036.83353,
    "lon_p": -69850.164866,
    "gas_price": 3.19
  },
  {
    "zipcode": "68663",
    "lat": 41.311897,
    "lon": -97.699293,
    "lat_p": 2032927.975874,
    "lon_p": -139296.108209,
    "gas_price": 3.19
  },
  {
    "zipcode": "68071",
    "lat": 42.236018,
    "lon": -96.47445,
    "lat_p": 2136409.05374,
    "lon_p": -34166.037722,
    "gas_price": 3.19
  },
  {
    "zipcode": "68045",
    "lat": 41.827293,
    "lon": -96.495259,
    "lat_p": 2090283.86893,
    "lon_p": -40404.636898,
    "gas_price": 3.19
  },
  {
    "zipcode": "68768",
    "lat": 41.998665,
    "lon": -97.06867,
    "lat_p": 2109423.14329,
    "lon_p": -87926.33275,
    "gas_price": 3.19
  },
  {
    "zipcode": "68315",
    "lat": 40.246087,
    "lon": -97.538426,
    "lat_p": 1915975.692821,
    "lon_p": -130527.946648,
    "gas_price": 3.19
  },
  {
    "zipcode": "68770",
    "lat": 42.562832,
    "lon": -96.76896,
    "lat_p": 2174930.556559,
    "lon_p": -63716.901977,
    "gas_price": 3.19
  },
  {
    "zipcode": "68056",
    "lat": 41.141242,
    "lon": -95.904413,
    "lat_p": 2014850.621676,
    "lon_p": 8061.82397,
    "gas_price": 3.19
  },
  {
    "zipcode": "68068",
    "lat": 41.397607,
    "lon": -96.207509,
    "lat_p": 2043522.856303,
    "lon_p": -17243.01317,
    "gas_price": 3.19
  },
  {
    "zipcode": "68316",
    "lat": 41.016883,
    "lon": -97.615764,
    "lat_p": 2002922.41165,
    "lon_p": -133673.913932,
    "gas_price": 3.19
  },
  {
    "zipcode": "68850",
    "lat": 40.825369,
    "lon": -99.735689,
    "lat_p": 1988518.670099,
    "lon_p": -310638.687794,
    "gas_price": 3.19
  },
  {
    "zipcode": "68330",
    "lat": 40.706587,
    "lon": -97.340493,
    "lat_p": 1967236.677561,
    "lon_p": -112239.254772,
    "gas_price": 3.19
  },
  {
    "zipcode": "68004",
    "lat": 42.008846,
    "lon": -96.629799,
    "lat_p": 2111485.440935,
    "lon_p": -54429.230894,
    "gas_price": 3.19
  },
  {
    "zipcode": "68376",
    "lat": 40.170932,
    "lon": -95.938093,
    "lat_p": 1905802.63105,
    "lon_p": 3879.31264,
    "gas_price": 3.19
  },
  {
    "zipcode": "68869",
    "lat": 40.999419,
    "lon": -98.883238,
    "lat_p": 2004828.787578,
    "lon_p": -236942.591889,
    "gas_price": 3.19
  },
  {
    "zipcode": "68345",
    "lat": 40.036972,
    "lon": -96.019253,
    "lat_p": 1893217.286468,
    "lon_p": -5883.288454,
    "gas_price": 3.19
  },
  {
    "zipcode": "68041",
    "lat": 41.236292,
    "lon": -96.487926,
    "lat_p": 2025298.637717,
    "lon_p": -41005.811177,
    "gas_price": 3.19
  },
  {
    "zipcode": "68073",
    "lat": 41.239278,
    "lon": -96.409298,
    "lat_p": 2025243.12769,
    "lon_p": -34491.209187,
    "gas_price": 3.19
  },
  {
    "zipcode": "68840",
    "lat": 40.757237,
    "lon": -98.880265,
    "lat_p": 1974540.37999,
    "lon_p": -241441.040046,
    "gas_price": 3.19
  },
  {
    "zipcode": "68845",
    "lat": 40.715762,
    "lon": -99.170594,
    "lat_p": 1973144.125423,
    "lon_p": -266225.053947,
    "gas_price": 3.19
  },
  {
    "zipcode": "68040",
    "lat": 41.285539,
    "lon": -96.738166,
    "lat_p": 2031449.744538,
    "lon_p": -60454.438582,
    "gas_price": 3.19
  },
  {
    "zipcode": "68849",
    "lat": 40.701456,
    "lon": -99.100884,
    "lat_p": 1969850.088854,
    "lon_p": -259585.829647,
    "gas_price": 3.19
  },
  {
    "zipcode": "68735",
    "lat": 42.149052,
    "lon": -98.454076,
    "lat_p": 2131462.863131,
    "lon_p": -204805.323021,
    "gas_price": 3.19
  },
  {
    "zipcode": "68872",
    "lat": 41.092872,
    "lon": -98.332166,
    "lat_p": 2011405.194808,
    "lon_p": -194650.373255,
    "gas_price": 3.19
  },
  {
    "zipcode": "68927",
    "lat": 40.511351,
    "lon": -99.626703,
    "lat_p": 1950823.351766,
    "lon_p": -306418.426329,
    "gas_price": 3.19
  },
  {
    "zipcode": "68714",
    "lat": 42.368708,
    "lon": -99.502761,
    "lat_p": 2156205.763294,
    "lon_p": -282222.136873,
    "gas_price": 3.19
  },
  {
    "zipcode": "68319",
    "lat": 40.936539,
    "lon": -97.758176,
    "lat_p": 1991963.720201,
    "lon_p": -146964.951371,
    "gas_price": 3.19
  },
  {
    "zipcode": "68871",
    "lat": 41.140399,
    "lon": -98.847845,
    "lat_p": 2018073.922112,
    "lon_p": -237603.649551,
    "gas_price": 3.19
  },
  {
    "zipcode": "68037",
    "lat": 40.984392,
    "lon": -96.126768,
    "lat_p": 1998405.898844,
    "lon_p": -10783.682168,
    "gas_price": 3.19
  },
  {
    "zipcode": "68403",
    "lat": 40.920448,
    "lon": -96.167063,
    "lat_p": 1990221.800101,
    "lon_p": -13685.782303,
    "gas_price": 3.19
  },
  {
    "zipcode": "68753",
    "lat": 42.844609,
    "lon": -99.455858,
    "lat_p": 2209646.850324,
    "lon_p": -283052.661923,
    "gas_price": 3.19
  },
  {
    "zipcode": "68792",
    "lat": 42.733216,
    "lon": -97.114261,
    "lat_p": 2193330.64851,
    "lon_p": -89843.62542,
    "gas_price": 3.19
  },
  {
    "zipcode": "68327",
    "lat": 40.010809,
    "lon": -97.621143,
    "lat_p": 1888384.832311,
    "lon_p": -135720.155187,
    "gas_price": 3.19
  },
  {
    "zipcode": "68420",
    "lat": 40.085545,
    "lon": -96.19124,
    "lat_p": 1896938.134165,
    "lon_p": -16050.554599,
    "gas_price": 3.19
  },
  {
    "zipcode": "68325",
    "lat": 40.013069,
    "lon": -97.751474,
    "lat_p": 1890920.989293,
    "lon_p": -148493.000666,
    "gas_price": 3.19
  },
  {
    "zipcode": "68943",
    "lat": 40.039151,
    "lon": -97.885905,
    "lat_p": 1892789.533465,
    "lon_p": -160418.652948,
    "gas_price": 3.19
  },
  {
    "zipcode": "68978",
    "lat": 40.063362,
    "lon": -98.093819,
    "lat_p": 1895708.758728,
    "lon_p": -176325.09305,
    "gas_price": 3.19
  }
]